ipyvtklink/__init__.py
ipyvtklink/_version.py
ipyvtklink/constants.py
ipyvtklink/throttler.py
ipyvtklink/viewer.py
ipyvtklink-0.2.3.dist-info/LICENSE
ipyvtklink-0.2.3.dist-info/METADATA
ipyvtklink-0.2.3.dist-info/WHEEL
ipyvtklink-0.2.3.dist-info/top_level.txt
ipyvtklink-0.2.3.dist-info/RECORD
