Metadata-Version: 2.1
Name: ipyvtklink
Version: 0.2.3
Summary: ipywidget for vtkRenderWindow
Home-page: https://github.com/Kitware/ipyvtklink
Author: Bane Sullivan
Author-email: bane.sullivan@kitware.com
License: BSD 3-Clause
Keywords: vtk plotting jupyter
Classifier: License :: OSI Approved :: BSD License
Classifier: Development Status :: 4 - Beta
Classifier: Framework :: IPython
Classifier: Intended Audience :: Developers
Classifier: Intended Audience :: Science/Research
Classifier: Topic :: Multimedia :: Graphics
Classifier: Programming Language :: Python :: 3
Classifier: Programming Language :: Python :: 3.5
Classifier: Programming Language :: Python :: 3.6
Classifier: Programming Language :: Python :: 3.7
Classifier: Programming Language :: Python :: 3.8
Requires-Python: >=3.5.*
License-File: LICENSE
Requires-Dist: ipycanvas (>=0.5.0)
Requires-Dist: ipyevents (>=0.8.0)
Requires-Dist: ipywidgets (~=7.7)
